arris_modem_status/__init__.py
arris_modem_status/exceptions.py
arris_modem_status/http_compatibility.py
arris_modem_status/instrumentation.py
arris_modem_status/models.py
arris_modem_status/py.typed
arris_modem_status/time_utils.py
arris_modem_status/cli/__init__.py
arris_modem_status/cli/__main__.py
arris_modem_status/cli/args.py
arris_modem_status/cli/connectivity.py
arris_modem_status/cli/formatters.py
arris_modem_status/cli/logging_setup.py
arris_modem_status/cli/main.py
arris_modem_status/client/__init__.py
arris_modem_status/client/auth.py
arris_modem_status/client/error_handler.py
arris_modem_status/client/http.py
arris_modem_status/client/main.py
arris_modem_status/client/parser.py
arris_modem_status-1.0.2.dist-info/licenses/LICENSE
arris_modem_status-1.0.2.dist-info/METADATA
arris_modem_status-1.0.2.dist-info/WHEEL
arris_modem_status-1.0.2.dist-info/entry_points.txt
arris_modem_status-1.0.2.dist-info/top_level.txt
arris_modem_status-1.0.2.dist-info/RECORD
