Metadata-Version: 2.4
Name: arris-modem-status
Version: 1.0.2
Summary: Unofficial Python client for Arris cable modem status via HNAP
Author: Charles Marshall
License: MIT
Project-URL: Homepage, https://github.com/csmarshall/arris-modem-status
Project-URL: Repository, https://github.com/csmarshall/arris-modem-status
Project-URL: Documentation, https://github.com/csmarshall/arris-modem-status#readme
Project-URL: Bug Tracker, https://github.com/csmarshall/arris-modem-status/issues
Project-URL: Changelog, https://github.com/csmarshall/arris-modem-status/blob/main/CHANGELOG.md
Project-URL: Source Code, https://github.com/csmarshall/arris-modem-status
Keywords: arris,modem,cable,router,DOCSIS,networking,monitoring,HNAP,status,diagnostics,internet
Classifier: Development Status :: 4 - Beta
Classifier: Environment :: Console
Classifier: Intended Audience :: Developers
Classifier: Intended Audience :: System Administrators
Classifier: Intended Audience :: Telecommunications Industry
Classifier: License :: OSI Approved :: MIT License
Classifier: Natural Language :: English
Classifier: Operating System :: OS Independent
Classifier: Programming Language :: Python :: 3
Classifier: Programming Language :: Python :: 3.9
Classifier: Programming Language :: Python :: 3.10
Classifier: Programming Language :: Python :: 3.11
Classifier: Programming Language :: Python :: 3.12
Classifier: Programming Language :: Python :: 3.13
Classifier: Programming Language :: Python :: 3 :: Only
Classifier: Topic :: Internet
Classifier: Topic :: System :: Hardware
Classifier: Topic :: System :: Monitoring
Classifier: Topic :: System :: Networking :: Monitoring
Classifier: Topic :: Software Development :: Libraries :: Python Modules
Classifier: Topic :: Utilities
Classifier: Typing :: Typed
Requires-Python: >=3.9
License-File: LICENSE
Requires-Dist: requests>=2.25.1
Requires-Dist: urllib3>=1.26.0
Provides-Extra: dev
Requires-Dist: setuptools>=78.1.1; extra == "dev"
Requires-Dist: ruff==0.12.7; extra == "dev"
Requires-Dist: black==25.1.0; extra == "dev"
Requires-Dist: mypy==1.17.1; extra == "dev"
Requires-Dist: pytest>=8.3.5; extra == "dev"
Requires-Dist: pytest-cov>=6.0.0; extra == "dev"
Requires-Dist: coverage[toml]>=7.6.10; extra == "dev"
Requires-Dist: bandit[toml]>=1.8.0; extra == "dev"
Requires-Dist: pip-audit>=2.8.0; extra == "dev"
Requires-Dist: interrogate>=1.7.0; extra == "dev"
Requires-Dist: vulture>=2.14; extra == "dev"
Requires-Dist: pre-commit>=4.0.2; extra == "dev"
Requires-Dist: pytest-mock>=3.10.0; extra == "dev"
Requires-Dist: bump-my-version>=0.17.0; extra == "dev"
Provides-Extra: debug
Requires-Dist: playwright>=1.40.0; extra == "debug"
Requires-Dist: selenium>=4.0.0; extra == "debug"
Requires-Dist: beautifulsoup4>=4.9.0; extra == "debug"
Requires-Dist: aiohttp>=3.8.0; extra == "debug"
Provides-Extra: all
Requires-Dist: arris-modem-status[debug,dev]; extra == "all"
Provides-Extra: test
Requires-Dist: pytest>=8.3.5; extra == "test"
Requires-Dist: pytest-cov>=4.0.0; extra == "test"
Requires-Dist: pytest-mock>=3.10.0; extra == "test"
Requires-Dist: pytest-timeout>=2.1.0; extra == "test"
Requires-Dist: pytest-asyncio<1.2.0,>=0.21.0; extra == "test"
Requires-Dist: coverage[toml]>=6.0.0; extra == "test"
Provides-Extra: build
Requires-Dist: build>=0.10.0; extra == "build"
Requires-Dist: twine>=4.0.0; extra == "build"
Requires-Dist: wheel>=0.40.0; extra == "build"
Dynamic: license-file
